kitconcept/__init__.py
kitconcept/api/__init__.py
kitconcept/api/_typing.py
kitconcept/api/logger.py
kitconcept/api/testing.py
kitconcept/api/addon/__init__.py
kitconcept/api/addon/_installer.py
kitconcept/api/content/__init__.py
kitconcept/api/content/_constrains.py
kitconcept/api/content/_serialize.py
kitconcept/api/env/__init__.py
kitconcept/api/exc/__init__.py
kitconcept/api/fti/__init__.py
kitconcept/api/fti/_fti.py
kitconcept/api/group/__init__.py
kitconcept/api/portal/__init__.py
kitconcept/api/redirection/__init__.py
kitconcept/api/redirection/_redirection.py
kitconcept/api/relation/__init__.py
kitconcept/api/tests/__init__.py
kitconcept/api/tests/test_addon.py
kitconcept/api/tests/test_content_constrains.py
kitconcept/api/tests/test_content_serialize.py
kitconcept/api/tests/test_fti.py
kitconcept/api/tests/test_redirection.py
kitconcept/api/tests/test_user.py
kitconcept/api/tests/test_vocabulary.py
kitconcept/api/user/__init__.py
kitconcept/api/user/_user.py
kitconcept/api/vocabulary/__init__.py
kitconcept/api/vocabulary/_vocabulary.py
kitconcept.api-1.0.0a4.dist-info/METADATA
kitconcept.api-1.0.0a4.dist-info/WHEEL
kitconcept.api-1.0.0a4.dist-info/top_level.txt
kitconcept.api-1.0.0a4.dist-info/RECORD
