Metadata-Version: 2.1
Name: kitconcept.api
Version: 1.0.0a4
Summary: Enhanced Python API for the Plone Content Management System
Home-page: https://kitconcept.com/
Author: kitconcept GmbH
Author-email: contact@kitconcept.com
License: GPL version 2
Keywords: Plone,CMS
Classifier: Development Status :: 5 - Production/Stable
Classifier: Environment :: Web Environment
Classifier: Framework :: Plone
Classifier: Framework :: Plone :: Core
Classifier: Framework :: Plone :: 5.2
Classifier: Framework :: Plone :: 6.0
Classifier: Framework :: Zope
Classifier: Framework :: Zope :: 5
Classifier: License :: OSI Approved :: GNU General Public License v2 (GPLv2)
Classifier: Operating System :: OS Independent
Classifier: Programming Language :: Python
Classifier: Programming Language :: Python :: 3.8
Classifier: Programming Language :: Python :: 3.9
Classifier: Topic :: Internet :: WWW/HTTP :: Dynamic Content
Requires-Python: >=3.8
Requires-Dist: setuptools (>=36.2)
Requires-Dist: Plone
Requires-Dist: plone.api (>=2.0.0a2)
Requires-Dist: plone.restapi
Provides-Extra: test
Requires-Dist: Products.CMFPlone ; extra == 'test'
Requires-Dist: plone.app.dexterity ; extra == 'test'
Requires-Dist: plone.app.testing ; extra == 'test'
Requires-Dist: plone.testing ; extra == 'test'
Requires-Dist: plone.restapi[test] ; extra == 'test'
Requires-Dist: zest.releaser[recommended] ; extra == 'test'
Requires-Dist: zestreleaser.towncrier ; extra == 'test'
